{
  "completedAt": "2026-06-19T22:38:53.968Z",
  "schemaVersion": "movebeta.release-gate-report.v1",
  "startedAt": "2026-06-19T22:38:40.038Z",
  "status": "pass",
  "steps": [
    {
      "command": "npm run quality",
      "completedAt": "2026-06-19T22:38:44.776Z",
      "durationMs": 4737,
      "exitCode": 0,
      "key": "quality",
      "label": "TypeScript and Vitest quality gate",
      "startedAt": "2026-06-19T22:38:40.039Z",
      "status": "pass"
    },
    {
      "command": "npm run model:movenet:readiness",
      "completedAt": "2026-06-19T22:38:50.744Z",
      "durationMs": 5968,
      "exitCode": 0,
      "key": "modelReadiness",
      "label": "MoveNet readiness report",
      "startedAt": "2026-06-19T22:38:44.776Z",
      "status": "pass"
    },
    {
      "command": "npm run model:analysis:replay",
      "completedAt": "2026-06-19T22:38:50.996Z",
      "durationMs": 253,
      "exitCode": 0,
      "key": "modelAnalysisReplay",
      "label": "Model-shaped analysis replay",
      "startedAt": "2026-06-19T22:38:50.744Z",
      "status": "pass"
    },
    {
      "command": "npm run native:qa:runbook",
      "completedAt": "2026-06-19T22:38:51.112Z",
      "durationMs": 115,
      "exitCode": 0,
      "key": "nativeQaRunbook",
      "label": "Native QA runbook generation",
      "startedAt": "2026-06-19T22:38:50.996Z",
      "status": "pass"
    },
    {
      "command": "npm run export:web",
      "completedAt": "2026-06-19T22:38:52.943Z",
      "durationMs": 1831,
      "exitCode": 0,
      "key": "webExport",
      "label": "Expo web export",
      "startedAt": "2026-06-19T22:38:51.112Z",
      "status": "pass"
    },
    {
      "command": "npm run release:eas:check",
      "completedAt": "2026-06-19T22:38:53.083Z",
      "durationMs": 140,
      "exitCode": 0,
      "key": "easStandard",
      "label": "EAS standard release check",
      "startedAt": "2026-06-19T22:38:52.943Z",
      "status": "pass"
    },
    {
      "command": "npm run security:audit",
      "completedAt": "2026-06-19T22:38:53.968Z",
      "durationMs": 885,
      "exitCode": 0,
      "key": "securityAudit",
      "label": "Moderate-or-higher dependency audit",
      "startedAt": "2026-06-19T22:38:53.083Z",
      "status": "pass"
    }
  ]
}
